{
  "approval_required": true,
  "blocked_actions": [
    "send_email",
    "external_send",
    "mailbox_mutation",
    "connector_call",
    "autonomous_execution",
    "customer_exposure",
    "deploy",
    "dns_mutation",
    "filesystem_write",
    "live_dispatch",
    "public_readiness_claim",
    "runtime_mutation",
    "secret_mutation",
    "terminal_closure",
    "calendar_write",
    "memory_topology_activation",
    "account_binding_claim",
    "provider_write"
  ],
  "blocked_component_ids": [
    "governance_core",
    "personal_assistant",
    "gmail_account_binding_gate"
  ],
  "can_call_connector": false,
  "can_claim_terminal_closure": false,
  "can_execute": false,
  "can_mutate": false,
  "expected_receipts": [
    "component_request_simulation_receipt",
    "component_path_preview_receipt",
    "authority_denial_receipt",
    "gmail_account_binding_evidence_receipt",
    "explicit_operator_send_approval_receipt",
    "live_send_authority_transition_receipt"
  ],
  "governed": true,
  "intent": "send_email_request",
  "live_execution_enabled": false,
  "mode": "foundation",
  "needed_evidence": [
    "gmail_account_binding_evidence_receipt",
    "explicit_operator_send_approval_receipt",
    "live_send_authority_transition_receipt"
  ],
  "outcome": "GovernanceBlocked",
  "reason": "email send is blocked until account-binding, approval, connector, and live-send witnesses exist",
  "request_text": "Send this email to the customer",
  "route": "/api/v1/components/simulate",
  "scenario_id": "send_email_blocked_preview",
  "schema_version": 1,
  "selected_component_ids": [
    "governance_core",
    "personal_assistant",
    "gmail_account_binding_gate"
  ],
  "simulation_id": "component_request_simulation.send_email_blocked_preview.v1",
  "simulation_is_not_execution_authority": true,
  "source_refs": {
    "proof_binding": "examples/component_proof_binding.foundation.json",
    "read_model": "examples/component_read_model.foundation.json",
    "registry": "examples/component_registry.foundation.json",
    "router_inventory": "examples/component_router_inventory.foundation.json"
  },
  "terminal_closure_required": true,
  "validators": [
    "component_request_simulation_validator",
    "component_request_simulation_route_tests",
    "component_read_model_validator"
  ]
}
